arbiter_ai/__init__.py
arbiter_ai/api.py
arbiter_ai/cli.py
arbiter_ai/py.typed
arbiter_ai/core/__init__.py
arbiter_ai/core/circuit_breaker.py
arbiter_ai/core/cost_calculator.py
arbiter_ai/core/estimation.py
arbiter_ai/core/exceptions.py
arbiter_ai/core/interfaces.py
arbiter_ai/core/llm_client.py
arbiter_ai/core/llm_client_pool.py
arbiter_ai/core/logging.py
arbiter_ai/core/middleware.py
arbiter_ai/core/models.py
arbiter_ai/core/monitoring.py
arbiter_ai/core/registry.py
arbiter_ai/core/retry.py
arbiter_ai/core/type_defs.py
arbiter_ai/core/types.py
arbiter_ai/core/validation.py
arbiter_ai/evaluators/__init__.py
arbiter_ai/evaluators/base.py
arbiter_ai/evaluators/custom_criteria.py
arbiter_ai/evaluators/factuality.py
arbiter_ai/evaluators/groundedness.py
arbiter_ai/evaluators/pairwise.py
arbiter_ai/evaluators/relevance.py
arbiter_ai/evaluators/semantic.py
arbiter_ai/evaluators/similarity_backends.py
arbiter_ai/storage/__init__.py
arbiter_ai/storage/base.py
arbiter_ai/storage/postgres.py
arbiter_ai/storage/redis.py
arbiter_ai/tools/__init__.py
arbiter_ai/verifiers/__init__.py
arbiter_ai/verifiers/base.py
arbiter_ai/verifiers/citation_verifier.py
arbiter_ai/verifiers/knowledge_base_verifier.py
arbiter_ai/verifiers/search_verifier.py
arbiter_ai-0.2.0.dist-info/licenses/LICENSE
arbiter_ai-0.2.0.dist-info/METADATA
arbiter_ai-0.2.0.dist-info/WHEEL
arbiter_ai-0.2.0.dist-info/entry_points.txt
arbiter_ai-0.2.0.dist-info/top_level.txt
arbiter_ai-0.2.0.dist-info/RECORD
