Metadata-Version: 2.4
Name: arbiter-ai
Version: 0.2.0
Summary: Native PydanticAI evaluation with automatic cost tracking
Author-email: Evan Volgas <evan.volgas@gmail.com>
License-Expression: MIT
Project-URL: Homepage, https://github.com/ashita-ai/arbiter
Project-URL: Documentation, https://github.com/ashita-ai/arbiter#readme
Project-URL: Repository, https://github.com/ashita-ai/arbiter
Project-URL: Issues, https://github.com/ashita-ai/arbiter/issues
Project-URL: Changelog, https://github.com/ashita-ai/arbiter/releases
Keywords: ai,llm,evaluation,testing,metrics,pydantic-ai,cost-tracking
Classifier: Development Status :: 4 - Beta
Classifier: Intended Audience :: Developers
Classifier: Programming Language :: Python :: 3
Classifier: Programming Language :: Python :: 3.11
Classifier: Programming Language :: Python :: 3.12
Classifier: Programming Language :: Python :: 3.13
Classifier: Programming Language :: Python :: 3.14
Classifier: Topic :: Scientific/Engineering :: Artificial Intelligence
Classifier: Topic :: Software Development :: Testing
Classifier: Typing :: Typed
Requires-Python: <3.15,>=3.11
License-File: LICENSE
Requires-Dist: pydantic>=2.12.0
Requires-Dist: pydantic-ai>=1.14.0
Requires-Dist: httpx>=0.28.0
Requires-Dist: openai>=2.0.0
Requires-Dist: python-dotenv>=1.0.1
Requires-Dist: aiofiles>=25.0.0
Requires-Dist: logfire>=4.0.0
Requires-Dist: numpy>=2.0.0
Requires-Dist: typing-extensions>=4.0.0
Requires-Dist: litellm>=1.50.0
Provides-Extra: anthropic
Requires-Dist: anthropic>=0.72.0; extra == "anthropic"
Provides-Extra: gemini
Requires-Dist: google-generativeai>=0.8.5; extra == "gemini"
Provides-Extra: mistral
Requires-Dist: mistralai>=1.0.0; extra == "mistral"
Provides-Extra: cohere
Requires-Dist: cohere>=5.0.0; extra == "cohere"
Provides-Extra: scale
Requires-Dist: faiss-cpu>=1.7.4; extra == "scale"
Requires-Dist: sentence-transformers>=2.2.0; extra == "scale"
Requires-Dist: pymilvus>=2.6.0; extra == "scale"
Provides-Extra: postgres
Requires-Dist: asyncpg>=0.29.0; extra == "postgres"
Requires-Dist: alembic>=1.13.0; extra == "postgres"
Requires-Dist: sqlalchemy>=2.0.0; extra == "postgres"
Requires-Dist: psycopg2-binary>=2.9.0; extra == "postgres"
Provides-Extra: redis
Requires-Dist: redis>=5.0.0; extra == "redis"
Provides-Extra: storage
Requires-Dist: arbiter-ai[postgres,redis]; extra == "storage"
Provides-Extra: verifiers
Requires-Dist: tavily-python>=0.5.0; extra == "verifiers"
Provides-Extra: cli
Requires-Dist: typer>=0.15.0; extra == "cli"
Requires-Dist: rich>=14.0.0; extra == "cli"
Provides-Extra: dev
Requires-Dist: pytest>=9.0.0; extra == "dev"
Requires-Dist: pytest-cov>=7.0.0; extra == "dev"
Requires-Dist: pytest-asyncio>=1.0.0; extra == "dev"
Requires-Dist: pytest-mock>=3.15.0; extra == "dev"
Requires-Dist: pytest-xdist>=3.8.0; extra == "dev"
Requires-Dist: black>=25.0.0; extra == "dev"
Requires-Dist: mypy>=1.18.0; extra == "dev"
Requires-Dist: ruff>=0.14.0; extra == "dev"
Requires-Dist: types-redis>=4.6.0; extra == "dev"
Requires-Dist: types-aiofiles>=25.0.0; extra == "dev"
Requires-Dist: rich>=14.0.0; extra == "dev"
Requires-Dist: mkdocs>=1.6.0; extra == "dev"
Requires-Dist: mkdocs-material>=9.7.0; extra == "dev"
Requires-Dist: mkdocstrings[python]>=0.30.0; extra == "dev"
Requires-Dist: pre-commit>=4.0.0; extra == "dev"
Requires-Dist: watchdog>=6.0.0; extra == "dev"
Requires-Dist: psutil>=7.0.0; extra == "dev"
Requires-Dist: setuptools>=80.0.0; extra == "dev"
Requires-Dist: build>=1.0.0; extra == "dev"
Requires-Dist: twine>=6.0.0; extra == "dev"
Provides-Extra: all
Requires-Dist: arbiter-ai[anthropic,cli,cohere,dev,gemini,mistral,scale,storage,verifiers]; extra == "all"
Dynamic: license-file
